ViNLP/__init__.py
ViNLP/data/Viet74K.txt
ViNLP/data/all-vietnamese-syllables.txt
ViNLP/datasets/__init__.py
ViNLP/datasets/base_dataset.py
ViNLP/datasets/chunk_dataset.py
ViNLP/datasets/dictionary.py
ViNLP/datasets/ner_dataset.py
ViNLP/datasets/pos_dataset.py
ViNLP/datasets/ss_dataset.py
ViNLP/datasets/ws_dataset.py
ViNLP/features/__init__.py
ViNLP/features/base_feature.py
ViNLP/features/chunk_feature.py
ViNLP/features/ner_feature.py
ViNLP/features/pos_feature.py
ViNLP/features/ss_feature.py
ViNLP/features/ws_feature.py
ViNLP/models/__init__.py
ViNLP/models/chunk_crf.py
ViNLP/models/ner_crf.py
ViNLP/models/pos_crf.py
ViNLP/models/ss_crf.py
ViNLP/models/ws_crf.py
ViNLP/pipeline/__init__.py
ViNLP/pipeline/chunking.py
ViNLP/pipeline/ner.py
ViNLP/pipeline/pos_tag.py
ViNLP/pipeline/sent_tokenize.py
ViNLP/pipeline/word_tokenize.py
ViNLP/pipeline/bin/chunk.crfsuite
ViNLP/pipeline/bin/ner.crfsuite
ViNLP/pipeline/bin/pos.crfsuite
ViNLP/pipeline/bin/ss.crfsuite
ViNLP/pipeline/bin/ws.crfsuite
ViNLP/utils/__init__.py
ViNLP/utils/file_io.py
ViNLP/utils/flatten.py
ViNLP/utils/regex_tokenize.py
ViNLP-1.2.106.dist-info/AUTHORS.md
ViNLP-1.2.106.dist-info/LICENSE
ViNLP-1.2.106.dist-info/METADATA
ViNLP-1.2.106.dist-info/WHEEL
ViNLP-1.2.106.dist-info/top_level.txt
ViNLP-1.2.106.dist-info/RECORD
