Metadata-Version: 2.1
Name: ViNLP
Version: 1.2.106
Summary: NLP package for Vietnamese
Home-page: https://github.com/hieunguyen1053/ViNLP
Author: Hieu Nguyen
Author-email: hieunguyen1053@outlook.com
License: MIT
Platform: UNKNOWN
Classifier: License :: OSI Approved :: MIT License
Classifier: Programming Language :: Python :: 3
Classifier: Programming Language :: Python :: 3.8
License-File: LICENSE
License-File: AUTHORS.md
Requires-Dist: sklearn-crfsuite (==0.3.6)
